someawesometestcode/__init__.py
someawesometestcode/anotherone.py
someawesometestcode-0.0.8.dist-info/METADATA
someawesometestcode-0.0.8.dist-info/WHEEL
someawesometestcode-0.0.8.dist-info/top_level.txt
someawesometestcode-0.0.8.dist-info/RECORD
