Metadata-Version: 2.1
Name: someawesometestcode
Version: 0.0.8
Summary: Testpackage
Home-page: UNKNOWN
Author: Tim Röthlisberger
Author-email: tim.roethlisberger@hotmail.com
License: UNKNOWN
Platform: UNKNOWN
Classifier: Programming Language :: Python :: 3
Classifier: License :: OSI Approved :: MIT License
Classifier: Operating System :: OS Independent
Requires-Python: >=3.6
